[
  {
    "id": 1,
    "game_id": "ffe5b43309eff2a1e0131998ff33abd6",
    "commence_time": "2026-03-16 23:10:00.000000",
    "home_team": "Атланта Хокс",
    "away_team": "Орландо Мэджик",
    "bet_type": "H2H",
    "pick": "Атланта Хокс",
    "odds": 1.69,
    "line": null,
    "our_prob": null,
    "edge": 12.0,
    "status": "PENDING",
    "result_score": null,
    "bookie": null,
    "sentiment_score": 0.35,
    "intel_summary": "Атланта на текущем отрезке демонстрирует признаки 'горячей' команды, что подтверждается настроениями в их сообществе и эффективностью ротации. Несмотря на то, что Орландо показывает солидную индивидуальную статистику (Банкеро выдает элитные цифры: 25.6 PPG при 54% с игры), их нестабильность в защите на выезде против организованных команд остается критическим фактором. Атланта обладает преимуществом домашней площадки и более сбалансированным распределением нагрузки, что в текущих реалиях регулярки дает им перевес.\n\nАнализ показывает, что рынок недооценивает текущий импульс 'Хокс'. Орландо, несмотря на недавнюю победу над Майами, часто испытывает проблемы с концентрацией в гостевых матчах. Учитывая, что Атланта сейчас находится в фазе поиска своей лучшей формы, а ролевые игроки вроде тех, кто упоминается в контексте прогресса, начинают давать глубину, вероятность победы хозяев выше заложенных букмекером 59.2%.\n\nМы видим здесь классический 'value spot'. Линия 1.69 выглядит привлекательно для ставки на фаворита, так как текущая форма лидеров Орландо может быть обманчива на фоне их общей выездной статистики. Ожидаем, что Атланта закроет матч за счет контроля темпа и более высокого процента реализации из краски, что нивелирует индивидуальные всплески Банкеро.",
    "notebook_id": null,
    "is_premium": 1,
    "confidence": "High",
    "is_published": 1,
    "published_at": "2026-03-16 12:56:08.992496",
    "created_at": "2026-03-16 11:27:28",
    "updated_at": "2026-03-16 18:38:25",
    "home_team_en": "Atlanta Hawks",
    "away_team_en": "Orlando Magic",
    "commence_time_display": "16.03 23:10"
  },
  {
    "id": 4,
    "game_id": "b2cf48e20e7ea3f4ee141bf67f8229d1",
    "commence_time": "2026-03-16 23:40:00.000000",
    "home_team": "Бруклин Нетс",
    "away_team": "Портленд Трэйл Блэйзерс",
    "bet_type": "SPREAD",
    "pick": "Бруклин Нетс",
    "odds": 1.93,
    "line": 10.5,
    "our_prob": null,
    "edge": 6.5,
    "status": "PENDING",
    "result_score": null,
    "bookie": null,
    "sentiment_score": 0.65,
    "intel_summary": "Ситуация для Portland Trail Blazers выглядит критической: команда находится в состоянии эмоционального выгорания после поражения от Филадельфии, где они продемонстрировали крайне неэффективную модель игры (53 попытки трехочковых при 18 потерях). Команда явно испытывает проблемы с дисциплиной и структурой атаки, что в условиях бэк-ту-бэк матча на выезде против Бруклина станет фатальным фактором. Усталость и отсутствие тактической гибкости делают их уязвимыми перед организованной защитой.\n\nBrooklyn Nets, несмотря на недавнее поражение от 76ers, выглядят более стабильно в плане ротации и психологического состояния. Внутренние дискуссии в стане Нетс о доверии внутри коллектива указывают на то, что команда находится в стадии поиска идентичности, но на домашнем паркете они традиционно играют более собранно. Отсутствие серьезных кадровых потерь у хозяев дает им преимущество в глубине состава, что критически важно для игры против измотанного соперника.\n\nРыночная вероятность (51.8% на победу хозяев) выглядит слегка заниженной, учитывая фактор усталости Портленда и их текущую игровую деградацию. Мы видим здесь перекос в сторону Бруклина, который должен закрывать этот матч за счет более высокого процента реализации и контроля темпа. Ожидаем, что Нетс воспользуются хаотичной игрой гостей и заберут победу в матче с низкой результативностью.",
    "notebook_id": null,
    "is_premium": 1,
    "confidence": "High",
    "is_published": 1,
    "published_at": "2026-03-16 18:41:51.562220",
    "created_at": "2026-03-16 11:28:52",
    "updated_at": "2026-03-16 18:41:51",
    "home_team_en": "Brooklyn Nets",
    "away_team_en": "Portland Trail Blazers",
    "commence_time_display": "16.03 23:40"
  }
]